fluidml/__about__.py
fluidml/__init__.py
fluidml/config_expansion.py
fluidml/dependency.py
fluidml/dolphin.py
fluidml/exception.py
fluidml/flow.py
fluidml/logging.py
fluidml/swarm.py
fluidml/task.py
fluidml/task_spec.py
fluidml/utils.py
fluidml/storage/__init__.py
fluidml/storage/base.py
fluidml/storage/controller.py
fluidml/storage/file_store.py
fluidml/storage/in_memory_store.py
fluidml/storage/mongo_db_store.py
fluidml/visualization/__init__.py
fluidml/visualization/ascii.py
fluidml/visualization/bokeh.py
fluidml/visualization/console.py
fluidml/visualization/graph_layout.py
fluidml/word_lists/__init__.py
fluidml/word_lists/adjectives.txt
fluidml/word_lists/nouns.txt
tests/__init__.py
tests/conftest.py
tests/integration/__init__.py
tests/integration/test_pipeline.py
tests/unit/__init__.py
tests/unit/fluidml/__init__.py
tests/unit/fluidml/test_config_expansion.py
tests/unit/fluidml/test_flow.py
tests/unit/fluidml/test_utils.py
tests/unit/fluidml/swarm/__init__.py
tests/unit/fluidml/visualization/__init__.py
fluidml-0.3.4.dist-info/LICENSE
fluidml-0.3.4.dist-info/METADATA
fluidml-0.3.4.dist-info/WHEEL
fluidml-0.3.4.dist-info/top_level.txt
fluidml-0.3.4.dist-info/RECORD
