Metadata-Version: 2.1
Name: fluidml
Version: 0.3.4
Summary: FluidML is a lightweight framework for developing machine learning pipelines. Focus only on your tasks and not the boilerplate!
Home-page: https://github.com/fluidml/fluidml/
Author: Lars Hillebrand, Rajkumar Ramamurthy
Author-email: hokage555@web.de
License: Apache-2.0
Download-URL: https://github.com/fluidml/fluidml/
Keywords: pipelines,machine-learning,parallel,deep-learning
Platform: UNKNOWN
Classifier: Development Status :: 4 - Beta
Classifier: Environment :: Console
Classifier: Framework :: IPython
Classifier: Intended Audience :: Developers
Classifier: Natural Language :: English
Classifier: Operating System :: Microsoft :: Windows
Classifier: Operating System :: MacOS
Classifier: Operating System :: POSIX :: Linux
Classifier: Programming Language :: Python :: 3.7
Classifier: Programming Language :: Python :: 3.8
Classifier: Programming Language :: Python :: 3.9
Classifier: Programming Language :: Python :: 3.10
Classifier: Programming Language :: Python :: 3.11
Classifier: Typing :: Typed
Requires-Python: >=3.7.0
Requires-Dist: bokeh >=2.4.3
Requires-Dist: grandalf >=0.7
Requires-Dist: metadict >=0.1.3
Requires-Dist: networkx >=2.5
Requires-Dist: pydantic >=2.0
Requires-Dist: rich >=9.13.0
Requires-Dist: tblib >=1.7.0
Provides-Extra: examples
Requires-Dist: datasets ; extra == 'examples'
Requires-Dist: flair ; extra == 'examples'
Requires-Dist: jupyterlab ; extra == 'examples'
Requires-Dist: numpy ; extra == 'examples'
Requires-Dist: pyyaml ; extra == 'examples'
Requires-Dist: requests ; extra == 'examples'
Requires-Dist: scikit-learn ; extra == 'examples'
Requires-Dist: tokenizers >=0.10.1 ; extra == 'examples'
Requires-Dist: torchtext >=0.8.1 ; extra == 'examples'
Requires-Dist: torch ; extra == 'examples'
Requires-Dist: tqdm ; extra == 'examples'
Provides-Extra: mongo-store
Requires-Dist: mongoengine >=0.27.0 ; extra == 'mongo-store'
Provides-Extra: tests
Requires-Dist: pytest >=7.0.0 ; extra == 'tests'
Requires-Dist: pytest-cov ; extra == 'tests'
Requires-Dist: black >=22.6 ; extra == 'tests'
Requires-Dist: pre-commit >=2.17.0 ; extra == 'tests'
